github_reviewboard_sync
