Metadata-Version: 1.1
Name: github-reviewboard-sync
Version: 0.1.5
Summary: Syncs pull requests with ReviewBoard submissions allowing you to create a pull request and review board submission at the same time
Home-page: https://github.com/timmartin19/github_reviewboard_sync
Author: Apptimize - Tim Martin
Author-email: martin@apptimize.com
License: MIT
Keywords: github_reviewboard_sync
Platform: UNKNOWN
Classifier: Development Status :: 2 - Pre-Alpha
Classifier: Intended Audience :: Developers
Classifier: License :: OSI Approved :: ISC License (ISCL)
Classifier: Natural Language :: English
Classifier: Programming Language :: Python :: 2
Classifier: Programming Language :: Python :: 2.7
Classifier: Programming Language :: Python :: 3
Classifier: Programming Language :: Python :: 3.4
Classifier: Programming Language :: Python :: 3.5
